propertiesLiBr/Stoffparameter_H2OLiBr_PK.py
propertiesLiBr/__init__.py
propertiesLiBr/functions.py
propertiesLiBr/h2o_IAPWS97/Stoffparameter_H2O.py
propertiesLiBr/h2o_IAPWS97/__init__.py
propertiesLiBr/h2o_IAPWS97/cpW.py
propertiesLiBr/h2o_IAPWS97/cpWp.py
propertiesLiBr/h2o_IAPWS97/cpreg1.py
propertiesLiBr/h2o_IAPWS97/cpreg2.py
propertiesLiBr/h2o_IAPWS97/densS.py
propertiesLiBr/h2o_IAPWS97/densSatLiqTW.py
propertiesLiBr/h2o_IAPWS97/densSatVapTW.py
propertiesLiBr/h2o_IAPWS97/densW.py
propertiesLiBr/h2o_IAPWS97/enthalpySatLiqTW.py
propertiesLiBr/h2o_IAPWS97/enthalpySatVapTW.py
propertiesLiBr/h2o_IAPWS97/enthalpyW.py
propertiesLiBr/h2o_IAPWS97/enthalpyreg1.py
propertiesLiBr/h2o_IAPWS97/enthalpyreg2.py
propertiesLiBr/h2o_IAPWS97/entropySatLiqTW.py
propertiesLiBr/h2o_IAPWS97/entropySatVapTW.py
propertiesLiBr/h2o_IAPWS97/entropyW.py
propertiesLiBr/h2o_IAPWS97/entropyreg1.py
propertiesLiBr/h2o_IAPWS97/entropyreg2.py
propertiesLiBr/h2o_IAPWS97/gamma0pipireg2.py
propertiesLiBr/h2o_IAPWS97/gamma0pireg2.py
propertiesLiBr/h2o_IAPWS97/gamma0pitaureg2.py
propertiesLiBr/h2o_IAPWS97/gamma0reg2.py
propertiesLiBr/h2o_IAPWS97/gamma0taureg2.py
propertiesLiBr/h2o_IAPWS97/gamma0tautaureg2.py
propertiesLiBr/h2o_IAPWS97/gammapipireg1.py
propertiesLiBr/h2o_IAPWS97/gammapireg1.py
propertiesLiBr/h2o_IAPWS97/gammapitaureg1.py
propertiesLiBr/h2o_IAPWS97/gammareg1.py
propertiesLiBr/h2o_IAPWS97/gammarpipireg2.py
propertiesLiBr/h2o_IAPWS97/gammarpireg2.py
propertiesLiBr/h2o_IAPWS97/gammarpitaureg2.py
propertiesLiBr/h2o_IAPWS97/gammarreg2.py
propertiesLiBr/h2o_IAPWS97/gammartaureg2.py
propertiesLiBr/h2o_IAPWS97/gammartautaureg2.py
propertiesLiBr/h2o_IAPWS97/gammataureg1.py
propertiesLiBr/h2o_IAPWS97/gammatautaureg1.py
propertiesLiBr/h2o_IAPWS97/lambthcon.py
propertiesLiBr/h2o_IAPWS97/pBound.py
propertiesLiBr/h2o_IAPWS97/pSatW.py
propertiesLiBr/h2o_IAPWS97/psivisc.py
propertiesLiBr/h2o_IAPWS97/spsoundW.py
propertiesLiBr/h2o_IAPWS97/spsoundreg1.py
propertiesLiBr/h2o_IAPWS97/spsoundreg2.py
propertiesLiBr-0.1.0.dist-info/LICENSE.txt
propertiesLiBr-0.1.0.dist-info/METADATA
propertiesLiBr-0.1.0.dist-info/WHEEL
propertiesLiBr-0.1.0.dist-info/top_level.txt
propertiesLiBr-0.1.0.dist-info/RECORD
